anysnap.py
anysnap-0.2.0.dist-info/METADATA
anysnap-0.2.0.dist-info/WHEEL
anysnap-0.2.0.dist-info/entry_points.txt
anysnap-0.2.0.dist-info/licenses/COPYING
anysnap-0.2.0.dist-info/RECORD
