Metadata-Version: 2.4
Name: AnySnap
Version: 0.2.0
Summary: Snapshot manager for various filesystems
Author-email: Olivier Schwander <olivier.schwander@chadok.info>
License-Expression: GPL-3.0-or-later
License-File: COPYING
Requires-Python: >=3.10
Requires-Dist: click>=8.1.7
Requires-Dist: plumbum>=1.9.0
